Metadata-Version: 1.2
Name: lib-estimate-sol
Version: 0.0.2
Summary: Script to estimate the size of solidity source code
Home-page: https://github.com/CoinFabrik/estimate-sol
Author: Coinfabrik team
License: mit
Platform: UNKNOWN
Classifier: Development Status :: 3 - Alpha
Classifier: License :: OSI Approved :: MIT License
Classifier: Operating System :: OS Independent
Requires-Python: >=3.8
